ppxf_sew/__init__.py
ppxf_sew/ew_fit.py
ppxf_sew/ew_util.py
ppxf_sew/example/example.ipynb
ppxf_sew/example/sps_models/BC03_SSP_tpl_chab.fits
ppxf_sew/example/test_data/spectrum.fit
ppxf_sew-0.5.5.dist-info/licenses/LICENSE
ppxf_sew-0.5.5.dist-info/METADATA
ppxf_sew-0.5.5.dist-info/WHEEL
ppxf_sew-0.5.5.dist-info/top_level.txt
ppxf_sew-0.5.5.dist-info/RECORD
