Metadata-Version: 2.4
Name: ppxf-sew
Version: 0.5.5
Summary: A method of stellar population synthesis based on ''Equivalent Widths spectrum'', utilizing pPXF for full-spectrum fitting
Author-email: Jiafeng Lu <jefferslu@live.com>
Classifier: Programming Language :: Python :: 3
Classifier: Development Status :: 4 - Beta
Classifier: License :: Other/Proprietary License
Classifier: Operating System :: OS Independent
Requires-Python: >=3.11
License-File: LICENSE
Requires-Dist: ppxf==9.2.1
Requires-Dist: numpy>=1.26.4
Requires-Dist: scipy>=1.12.0
Dynamic: license-file
